tiquations/__init__.py
tiquations/chemistry.py
tiquations/constants.py
tiquations/convert.py
tiquations/equations.py
tiquations/planets.py
tiquations-2.0.dist-info/LICENSE.txt
tiquations-2.0.dist-info/METADATA
tiquations-2.0.dist-info/WHEEL
tiquations-2.0.dist-info/top_level.txt
tiquations-2.0.dist-info/RECORD
