Metadata-Version: 2.1
Name: tiquations
Version: 2.0
Summary: Tiquations is an Open-Source Python package that is aimed at giving mathematicians and scientists easy access to important equations that they may use often. It was made in python 3.7 and should work on all versions higher than 3.0.
Home-page: https://tiquations.com
Author: Tinos Psomadakis
Author-email: tinosps@gmail.com
License: UNKNOWN
Platform: UNKNOWN
Classifier: Programming Language :: Python :: 3
Classifier: License :: OSI Approved :: MIT License
Classifier: Operating System :: OS Independent
